LICENSE.txt
MANIFEST.in
README.adoc
setup.py
examples/add_affinity_label.py
examples/add_bond.py
examples/add_cluster.py
examples/add_data_center.py
examples/add_disks.py
examples/add_fence_agent.py
examples/add_floating_disk.py
examples/add_group.py
examples/add_host.py
examples/add_independet_vm.py
examples/add_instance_type.py
examples/add_iscsi_data_storage_domain.py
examples/add_logical_network.py
examples/add_lun_disk_to_vm.py
examples/add_mac_pool.py
examples/add_nfs_data_storage_domain.py
examples/add_nfs_iso_storage_domain.py
examples/add_openstack_image_provider.py
examples/add_role.py
examples/add_tag.py
examples/add_template.py
examples/add_user_ssh_public_key.py
examples/add_vm.py
examples/add_vm_disk.py
examples/add_vm_from_template_version.py
examples/add_vm_nic.py
examples/add_vm_pool.py
examples/add_vm_snapshot.py
examples/add_vm_with_sysprep.py
examples/add_vnc_console.py
examples/assign_affinity_label_to_vm.py
examples/assign_network_to_cluster.py
examples/assign_permission.py
examples/assign_permission_to_vms.py
examples/assign_tag_to_vm.py
examples/asynchronous_inventory.py
examples/attach_nfs_data_storage_domain.py
examples/attach_nfs_iso_storage_domain.py
examples/backup_vm.py
examples/cancel_transfer.py
examples/change_host_cluster.py
examples/change_master.py
examples/change_vm_cd.py
examples/checkpoints.py
examples/checksum_disk.py
examples/checksum_image.py
examples/clone_vm_from_snapshot.py
examples/connection_builder.py
examples/data_center_maintenance.py
examples/deactivate_disk_attachment.py
examples/delete_disks.py
examples/disable_compression.py
examples/download_disk.py
examples/download_disk_snapshot.py
examples/download_vm_ovf.py
examples/enable_serial_console.py
examples/export_template.py
examples/export_template_as_ova.py
examples/export_vm.py
examples/export_vm_as_ova.py
examples/extend_disk.py
examples/fix_dup_nic_macs.py
examples/follow_vm_links.py
examples/get_display_ticket.py
examples/get_vm_ip.py
lib/ovirt_engine_sdk_python.egg-info/PKG-INFO
lib/ovirt_engine_sdk_python.egg-info/SOURCES.txt
lib/ovirt_engine_sdk_python.egg-info/dependency_links.txt
lib/ovirt_engine_sdk_python.egg-info/requires.txt
lib/ovirt_engine_sdk_python.egg-info/top_level.txt
