Metadata-Version: 2.4
Name: ovirt-engine-sdk-python
Version: 4.6.3
Summary: Python SDK for oVirt Engine API
Author: oVirt Developers
Author-email: devel@ovirt.org
License: Apache-2.0
Classifier: Development Status :: 5 - Production/Stable
Classifier: Environment :: Console
Classifier: Intended Audience :: Developers
Classifier: Intended Audience :: System Administrators
Classifier: Operating System :: OS Independent
Classifier: Programming Language :: Python :: 3
License-File: LICENSE.txt
Requires-Dist: pycurl>=7.19.0
Dynamic: author
Dynamic: author-email
Dynamic: classifier
Dynamic: license
Dynamic: license-file
Dynamic: requires-dist
Dynamic: summary
